setup.py
logist/__init__.py
logist/tests.py
logist.egg-info/PKG-INFO
logist.egg-info/SOURCES.txt
logist.egg-info/dependency_links.txt
logist.egg-info/not-zip-safe
logist.egg-info/requires.txt
logist.egg-info/top_level.txt