Metadata-Version: 1.1
Name: logist
Version: 0.92
Summary: Easy logging system for humans and machines
Home-page: https://github.com/atmb4u/logist
Author: Anoop Thomas Mathew
Author-email: atmb4u@gmail.com
License: BSD
Platform: UNKNOWN
Requires: redis
